{"tokens": ["NHS", "hospital", "trusts", "in", "England", "reported", "55", "cyber", "attacks", "in", "2016", ",", "according", "to", "data", "obtained", "by", "the", "BBC", ".", "The", "figures", "come", "from", "NHS", "Digital", ",", "which", "oversees", "cyber", "security", ",", "and", "show", "an", "increase", "on", "16", "attacks", "in", "2015", ".", "NHS", "Digital", "said", "the", "figures", "showed", "a", "\"", "rise", "in", "reporting", ",", "not", "necessarily", "a", "rise", "in", "cyber", "attacks", "\"", ".", "But", "Oliver", "Farnan", ",", "from", "the", "Oxford", "Cyber", "Security", "Centre", ",", "said", "ransomware", "attacks", "had", "become", "more", "common", ".", "'", "The", "risk", "is", "going", "to", "increase", "'", "Ransomware", "is", "software", "that", "locks", "computer", "systems", "and", "then", "demands", "a", "ransom", "to", "unlock", "the", "data", ".", "Oxford", "University", "Hospitals", "NHS", "Foundation", "Trust", "(", "OUH", ")", "repelled", "five", "ransomware", "attacks", "in", "2016", ".", "\"", "That", "is", "something", "a", "number", "of", "hospitals", "have", "seen", "and", "is", "potentially", "quite", "worrying", ",", "\"", "said", "Dr", "Chris", "Bunch", "from", "OUH", ".", "He", "added", ":", "\"", "Across", "the", "health", "service", "we", "are", "still", "to", "a", "very", "large", "extent", "paper", "-", "based", "...", "and", "as", "we", "move", "increasingly", "towards", "digital", "records", "the", "risk", "is", "going", "to", "increase", ".", "\"", "Leeds", "Teaching", "Hospitals", "NHS", "Trust", "reported", "four", "ransomware", "attacks", "in", "2016", ",", "and", "University", "Hospitals", "Bristol", "NHS", "Foundation", "Trust", "and", "Kings", "College", "Hospital", "NHS", "Foundation", "Trust", "sustained", "three", "ransomware", "attacks", "each", "last", "year", ".", "No", "patient", "data", "was", "lost", "in", "any", "of", "the", "attacks", "on", "the", "trusts", "and", "a", "spokesperson", "for", "Kings", "College", "Hospitals", "Trust", "said", "it", "had", "a", "cyber", "security", "response", "plan", "that", "it", "continually", "reviewed", "and", "monitored", ".", "Oliver", "Farnan", "from", "the", "Oxford", "Cyber", "Security", "Centre", ",", "said", "it", "was", "hard", "to", "know", "if", "enough", "money", "was", "being", "spent", "on", "security", "in", "the", "NHS", ".", "\"", "Money", "is", "only", "really", "spent", "on", "security", "once", "everything", "else", "is", "up", "and", "running", "and", "in", "place", "...", "it", "always", "comes", "second", ",", "\"", "he", "said", ".", "But", "David", "Emm", ",", "principal", "security", "researcher", "at", "internet", "security", "firm", "Kaspersky", "Lab", ",", "said", "basic", "steps", "such", "as", "backing", "up", "data", "could", "make", "a", "difference", ".", "\"", "Ransomware", "is", "a", "very", "blunt", "instrument", ",", "if", "you", "have", "a", "back", "-", "up", "of", "data", "then", "you", "are", "not", "in", "a", "position", "where", "people", "can", "extort", "money", "in", "that", "way", ",", "\"", "he", "said", ".", "However", ",", "Mr", "Emm", "said", "public", "bodies", "faced", "specific", "challenges", ",", "and", "added", "that", "money", "was", "an", "issue", ".", "\"", "They", "have", "lots", "of", "people", "accessing", "the", "systems", ",", "there", "is", "lots", "of", "data", "moving", "in", "and", "out", "of", "the", "organisation", ",", "that", "does", "actually", "make", "it", "harder", "to", "secure", "that", "information", ",", "\"", "he", "said", ".", "NHS", "Digital", "said", "it", "had", "established", "CareCERT", "which", "issues", "notices", "about", "the", "national", "threat", "level", "and", "publishes", "advice", "on", "good", "practice", ".", "It", "said", "its", "launch", "in", "October", "2015", "has", "contributed", "to", "the", "increase", "in", "the", "reporting", "of", "cyber", "attacks", ",", "and", "that", "more", "than", "100", "organisations", "had", "received", "on", "-", "site", "assessments", "to", "improve", "security", "."], "Event 1": {"trigger": {"start": 99, "end": 102, "text": ["demands", "a", "ransom"]}, "event_type": "Ransom", "argument": [{"start": 94, "end": 97, "text": ["locks", "computer", "systems"]}, {"start": 90, "end": 91, "text": ["Ransomware"]}], "Causal": [{"start": 94, "end": 97, "text": ["locks", "computer", "systems"]}], "Effect": []}, "Event 2": {"trigger": {"start": 75, "end": 77, "text": ["ransomware", "attacks"]}, "event_type": "Ransom", "argument": [], "Causal": [], "Effect": []}, "Event 3": {"trigger": {"start": 362, "end": 364, "text": ["extort", "money"]}, "event_type": "Ransom", "argument": [{"start": 360, "end": 361, "text": ["people"]}, {"start": 336, "end": 337, "text": ["Ransomware"]}], "Causal": [{"start": 360, "end": 361, "text": ["people"]}], "Effect": []}, "Event 4": {"trigger": {"start": 117, "end": 120, "text": ["five", "ransomware", "attacks"]}, "event_type": "Ransom", "argument": [{"start": 107, "end": 116, "text": ["Oxford", "University", "Hospitals", "NHS", "Foundation", "Trust", "(", "OUH", ")"]}, {"start": 121, "end": 122, "text": ["2016"]}], "Causal": [], "Effect": [{"start": 107, "end": 116, "text": ["Oxford", "University", "Hospitals", "NHS", "Foundation", "Trust", "(", "OUH", ")"]}]}, "Event 5": {"trigger": {"start": 190, "end": 192, "text": ["ransomware", "attacks"]}, "event_type": "Ransom", "argument": [{"start": 193, "end": 194, "text": ["2016"]}, {"start": 183, "end": 188, "text": ["Leeds", "Teaching", "Hospitals", "NHS", "Trust"]}], "Causal": [], "Effect": [{"start": 183, "end": 188, "text": ["Leeds", "Teaching", "Hospitals", "NHS", "Trust"]}]}, "Event 6": {"trigger": {"start": 210, "end": 213, "text": ["three", "ransomware", "attacks"]}, "event_type": "Ransom", "argument": [{"start": 214, "end": 216, "text": ["last", "year"]}, {"start": 196, "end": 202, "text": ["University", "Hospitals", "Bristol", "NHS", "Foundation", "Trust"]}, {"start": 203, "end": 209, "text": ["Kings", "College", "Hospital", "NHS", "Foundation", "Trust"]}], "Causal": [], "Effect": [{"start": 196, "end": 202, "text": ["University", "Hospitals", "Bristol", "NHS", "Foundation", "Trust"]}, {"start": 203, "end": 209, "text": ["Kings", "College", "Hospital", "NHS", "Foundation", "Trust"]}]}}