{"tokens": ["Northrop", "Grumman", "has", "admitted", "one", "of", "its", "internal", "portals", "was", "broken", "into", ",", "exposing", "employees", "'", "sensitive", "tax", "records", "to", "miscreants", ".", "In", "a", "letter", "[", "PDF", "]", "to", "workers", "and", "the", "California", "Attorney", "General", "'s", "office", ",", "the", "aerospace", "contractor", "said", "that", "between", "April", "18", ",", "2016", "and", "March", "29", ",", "2017", ",", "crooks", "infiltrated", "the", "website", ",", "allowing", "them", "to", "access", "staffers", "'", "W", "-", "2", "paperwork", "for", "the", "2016", "tax", "year", ".", "These", "W", "-", "2", "forms", "can", "be", "used", "by", "identity", "thieves", "to", "claim", "tax", "rebates", "owed", "to", "employees", ",", "allowing", "the", "crims", "to", "pocket", "victims", "'", "money", ".", "The", "corp", "sent", "out", "its", "warning", "letters", "on", "April", "18", ",", "the", "last", "day", "to", "file", "2016", "tax", "returns", ".", "\"", "The", "personal", "information", "that", "may", "have", "been", "accessed", "includes", "your", "name", ",", "address", ",", "work", "email", "address", ",", "work", "phone", "number", ",", "Social", "Security", "number", ",", "employer", "identification", "number", ",", "and", "wage", "and", "tax", "information", ",", "as", "well", "as", "any", "personal", "phone", "number", ",", "personal", "email", "address", ",", "or", "answers", "to", "customized", "security", "questions", "that", "you", "may", "have", "entered", "on", "the", "W", "-", "2", "online", "portal", ",", "\"", "the", "contractor", "told", "its", "employees", ".", "The", "Stealth", "Bomber", "maker", "says", "it", "will", "provide", "all", "of", "the", "exposed", "workers", "with", "three", "years", "of", "free", "identity", "-", "theft", "monitoring", "services", ".", "Northrop", "Grumman", "has", "also", "disabled", "access", "to", "the", "W", "-", "2", "portal", "through", "any", "method", "other", "than", "its", "internal", "single", "sign", "-", "on", "tool", ".", "The", "aerospace", "giant", "said", "it", "farmed", "out", "its", "tax", "portal", "to", "Equifax", "Workforce", "Solutions", ",", "which", "was", "working", "with", "the", "defense", "giant", "to", "get", "to", "the", "bottom", "of", "the", "intrusion", ".", "\"", "Promptly", "after", "confirming", "the", "incident", ",", "we", "worked", "with", "Equifax", "to", "determine", "the", "details", "of", "the", "issue", ",", "\"", "Northrop", "told", "its", "teams", ".", "\"", "Northrop", "Grumman", "and", "Equifax", "are", "coordinating", "with", "law", "enforcement", "authorities", "to", "assist", "them", "in", "their", "investigation", "of", "recent", "incidents", "involving", "unauthorized", "actors", "gaining", "access", "to", "individuals", "\u2019", "personal", "information", "through", "the", "W", "-", "2", "online", "portal", ".", "\"", "According", "to", "Equifax", ",", "the", "portal", "was", "accessed", "not", "by", "hackers", "but", "by", "someone", "using", "stolen", "login", "details", ".", "\"", "We", "are", "investigating", "alleged", "unauthorized", "access", "to", "our", "online", "portal", "where", "a", "person", "or", "persons", "using", "stolen", "credentials", "accessed", "W", "-", "2", "information", "of", "a", "limited", "number", "of", "individuals", ",", "\"", "an", "Equifax", "spokesperson", "told", "El", "Reg", "on", "Monday", ".", "\"", "Based", "on", "the", "investigation", "to", "date", ",", "Equifax", "has", "no", "reason", "to", "believe", "that", "its", "systems", "were", "compromised", "or", "that", "it", "was", "the", "source", "of", "the", "information", "used", "to", "gain", "access", "to", "the", "online", "portal", ".", "\""], "trigger": [{"start": 326, "end": 327, "text": ["gaining", "access"], "event": "Databreach"}, {"start": 348, "end": 349, "text": ["was", "accessed"], "event": "Databreach"}, {"start": 321, "end": 322, "text": ["recent", "incidents"], "event": "Databreach"}, {"start": 366, "end": 367, "text": ["unauthorized", "access"], "event": "Databreach"}, {"start": 380, "end": 380, "text": ["accessed"], "event": "Databreach"}, {"start": 419, "end": 420, "text": ["were", "compromised"], "event": "Databreach"}, {"start": 432, "end": 433, "text": ["gain", "access"], "event": "Databreach"}, {"start": 13, "end": 13, "text": ["exposing"], "event": "Databreach"}, {"start": 62, "end": 62, "text": ["access"], "event": "Databreach"}, {"start": 129, "end": 131, "text": ["have", "been", "accessed"], "event": "Databreach"}], "Entities": [[{"start": 324, "end": 325, "text": ["unauthorized", "actors"], "type": "Person"}, {"start": 331, "end": 332, "text": ["personal", "information"], "type": "PII"}, {"start": 334, "end": 339, "text": ["the", "W", "-", "2", "online", "portal"], "type": "System"}, {"start": 329, "end": 329, "text": ["individuals"], "type": "Person"}], [{"start": 346, "end": 347, "text": ["the", "portal"], "type": "System"}, {"start": 352, "end": 352, "text": ["hackers"], "type": "Person"}, {"start": 355, "end": 355, "text": ["someone"], "type": "Person"}, {"start": 356, "end": 359, "text": ["using", "stolen", "login", "details"], "type": "Capabilities"}], [{"start": 307, "end": 307, "text": ["Equifax"], "type": "Organization"}, {"start": 304, "end": 305, "text": ["Northrop", "Grumman"], "type": "Organization"}], [{"start": 369, "end": 371, "text": ["our", "online", "portal"], "type": "System"}], [{"start": 377, "end": 379, "text": ["using", "stolen", "credentials"], "type": "Capabilities"}, {"start": 381, "end": 384, "text": ["W", "-", "2", "information"], "type": "PII"}, {"start": 390, "end": 390, "text": ["individuals"], "type": "Person"}, {"start": 376, "end": 376, "text": ["persons"], "type": "Person"}, {"start": 373, "end": 374, "text": ["a", "person"], "type": "Person"}], [{"start": 410, "end": 410, "text": ["Equifax"], "type": "Organization"}, {"start": 417, "end": 418, "text": ["its", "systems"], "type": "System"}], [{"start": 435, "end": 437, "text": ["the", "online", "portal"], "type": "System"}], [{"start": 0, "end": 1, "text": ["Northrop", "Grumman"], "type": "Organization"}, {"start": 16, "end": 18, "text": ["sensitive", "tax", "records"], "type": "Data"}, {"start": 20, "end": 20, "text": ["miscreants"], "type": "Person"}, {"start": 14, "end": 14, "text": ["employees"], "type": "Person"}], [{"start": 65, "end": 68, "text": ["W", "-", "2", "paperwork"], "type": "PII"}, {"start": 55, "end": 57, "text": ["infiltrated", "the", "website"], "type": "Capabilities"}, {"start": 54, "end": 54, "text": ["crooks"], "type": "Person"}, {"start": 63, "end": 63, "text": ["staffers"], "type": "Person"}, {"start": 71, "end": 71, "text": ["2016"], "type": "Time"}, {"start": 87, "end": 89, "text": ["claim", "tax", "rebates"], "type": "Purpose"}, {"start": 38, "end": 40, "text": ["the", "aerospace", "contractor"], "type": "Organization"}, {"start": 43, "end": 52, "text": ["between", "April", "18", ",", "2016", "and", "March", "29", ",", "2017"], "type": "Time"}], [{"start": 124, "end": 126, "text": ["The", "personal", "information"], "type": "PII"}, {"start": 175, "end": 177, "text": ["customized", "security", "questions"], "type": "Data"}, {"start": 173, "end": 173, "text": ["answers"], "type": "Data"}, {"start": 168, "end": 170, "text": ["personal", "email", "address"], "type": "PII"}, {"start": 164, "end": 166, "text": ["personal", "phone", "number"], "type": "PII"}, {"start": 155, "end": 158, "text": ["wage", "and", "tax", "information"], "type": "Data"}, {"start": 150, "end": 152, "text": ["employer", "identification", "number"], "type": "PII"}, {"start": 146, "end": 148, "text": ["Social", "Security", "number"], "type": "PII"}, {"start": 142, "end": 144, "text": ["work", "phone", "number"], "type": "PII"}, {"start": 138, "end": 140, "text": ["work", "email", "address"], "type": "PII"}, {"start": 136, "end": 136, "text": ["address"], "type": "PII"}, {"start": 133, "end": 134, "text": ["your", "name"], "type": "PII"}]], "Causal": [[{"start": 324, "end": 325, "text": ["unauthorized", "actors"], "type": "Person"}, {"start": 334, "end": 339, "text": ["the", "W", "-", "2", "online", "portal"], "type": "System"}], [{"start": 355, "end": 355, "text": ["someone"], "type": "Person"}, {"start": 356, "end": 359, "text": ["using", "stolen", "login", "details"], "type": "Capabilities"}], [], [], [{"start": 377, "end": 379, "text": ["using", "stolen", "credentials"], "type": "Capabilities"}, {"start": 376, "end": 376, "text": ["persons"], "type": "Person"}, {"start": 373, "end": 374, "text": ["a", "person"], "type": "Person"}], [], [{"start": 435, "end": 437, "text": ["the", "online", "portal"], "type": "System"}], [{"start": 20, "end": 20, "text": ["miscreants"], "type": "Person"}], [{"start": 55, "end": 57, "text": ["infiltrated", "the", "website"], "type": "Capabilities"}, {"start": 54, "end": 54, "text": ["crooks"], "type": "Person"}], []], "Effect": [[{"start": 331, "end": 332, "text": ["personal", "information"], "type": "PII"}, {"start": 329, "end": 329, "text": ["individuals"], "type": "Person"}], [{"start": 346, "end": 347, "text": ["the", "portal"], "type": "System"}], [{"start": 307, "end": 307, "text": ["Equifax"], "type": "Organization"}, {"start": 304, "end": 305, "text": ["Northrop", "Grumman"], "type": "Organization"}], [{"start": 369, "end": 371, "text": ["our", "online", "portal"], "type": "System"}], [{"start": 381, "end": 384, "text": ["W", "-", "2", "information"], "type": "PII"}, {"start": 390, "end": 390, "text": ["individuals"], "type": "Person"}], [{"start": 410, "end": 410, "text": ["Equifax"], "type": "Organization"}, {"start": 417, "end": 418, "text": ["its", "systems"], "type": "System"}], [], [{"start": 0, "end": 1, "text": ["Northrop", "Grumman"], "type": "Organization"}, {"start": 16, "end": 18, "text": ["sensitive", "tax", "records"], "type": "Data"}, {"start": 14, "end": 14, "text": ["employees"], "type": "Person"}], [{"start": 65, "end": 68, "text": ["W", "-", "2", "paperwork"], "type": "PII"}, {"start": 63, "end": 63, "text": ["staffers"], "type": "Person"}, {"start": 87, "end": 89, "text": ["claim", "tax", "rebates"], "type": "Purpose"}, {"start": 38, "end": 40, "text": ["the", "aerospace", "contractor"], "type": "Organization"}], [{"start": 124, "end": 126, "text": ["The", "personal", "information"], "type": "PII"}, {"start": 175, "end": 177, "text": ["customized", "security", "questions"], "type": "Data"}, {"start": 173, "end": 173, "text": ["answers"], "type": "Data"}, {"start": 168, "end": 170, "text": ["personal", "email", "address"], "type": "PII"}, {"start": 164, "end": 166, "text": ["personal", "phone", "number"], "type": "PII"}, {"start": 155, "end": 158, "text": ["wage", "and", "tax", "information"], "type": "Data"}, {"start": 150, "end": 152, "text": ["employer", "identification", "number"], "type": "PII"}, {"start": 146, "end": 148, "text": ["Social", "Security", "number"], "type": "PII"}, {"start": 142, "end": 144, "text": ["work", "phone", "number"], "type": "PII"}, {"start": 138, "end": 140, "text": ["work", "email", "address"], "type": "PII"}, {"start": 136, "end": 136, "text": ["address"], "type": "PII"}, {"start": 133, "end": 134, "text": ["your", "name"], "type": "PII"}]]}