{"tokens": ["Mere", "days", "after", "thousands", "of", "MongoDB", "databases", "were", "hit", "by", "ransomware", "attacks", ",", "cybercriminals", "have", "set", "their", "sights", "on", "ElasticSearch", "servers", ",", "according", "to", "reports", ".", "Hackers", "have", "reportedly", "hijacked", "insecure", "servers", "exposed", "to", "the", "internet", "with", "weak", "and", "easy", "-", "to", "-", "guess", "passwords", ".", "ElasticSearch", "is", "a", "Java", "-", "based", "search", "engine", ",", "commonly", "used", "by", "enterprises", "for", "information", "cataloguing", "and", "data", "analysis", ".", "According", "to", "security", "researcher", "Niall", "Merrigan", ",", "who", "has", "been", "monitoring", "the", "attacks", ",", "the", "cybercriminals", "are", "currently", "closing", "in", "on", "around", "3,000", "ElasticSearch", "servers", ".", "Merrigan", "told", "IBTimes", "UK", ":", "\"", "We", "found", "the", "first", "one", "on", "the", "12th", "of", "Jan", "and", "then", "started", "tracking", "the", "different", "IOCs", "(", "Indicators", "Of", "Compromise", ")", ".", "The", "first", "actor", "has", "levelled", "off", "and", "looks", "like", "it", "has", "stopped", ".", "However", ",", "a", "second", "and", "third", "actor", "have", "joined", "in", "and", "are", "continuing", "to", "compromise", "servers", ".", "\"", "Attackers", "are", "finding", "open", "servers", "where", "there", "is", "no", "authentication", "at", "all", ".", "This", "can", "be", "done", "via", "a", "number", "of", "services", "and", "tools", ".", "Unfortunately", ",", "system", "admins", "and", "developers", "have", "been", "leaving", "these", "unauthenticated", "systems", "online", "for", "a", "while", "and", "attackers", "are", "just", "picking", "off", "the", "low", "hanging", "fruit", "right", "now", ".", "\"", "The", "recent", "MongoDB", "attacks", "saw", "hackers", "demand", "ransom", "and", "erasing", "data", "to", "ensure", "victims", "'", "compliance", ".", "In", "the", "ongoing", "ElasticSearch", "attacks", ",", "the", "cybercriminals", "demand", "a", "ransom", "of", "0.2", "Bitcoins", ",", "according", "to", "a", "report", "by", "BleepingComputer", ".", "However", ",", "according", "to", "Merrigan", ",", "$", "20,000", "in", "Bitcoins", "have", "already", "been", "paid", "by", "victims", "of", "the", "MongoDB", "attack", ".", "Despite", "paying", "the", "ransom", ",", "the", "victims", "have", "not", "received", "their", "data", "back", ".", "\"", "So", "in", "this", "case", "it", "is", "a", "scam", ",", "\"", "the", "researcher", "said", "."], "trigger": [{"start": 207, "end": 210, "text": ["The", "recent", "MongoDB", "attacks"], "event": "Ransom"}, {"start": 213, "end": 214, "text": ["demand", "ransom"], "event": "Ransom"}, {"start": 7, "end": 11, "text": ["were", "hit", "by", "ransomware", "attacks"], "event": "Ransom"}, {"start": 32, "end": 32, "text": ["exposed"], "event": "DiscoverVulnerability"}, {"start": 77, "end": 78, "text": ["the", "attacks"], "event": "Ransom"}, {"start": 225, "end": 228, "text": ["the", "ongoing", "ElasticSearch", "attacks"], "event": "Ransom"}, {"start": 232, "end": 234, "text": ["demand", "a", "ransom"], "event": "Ransom"}, {"start": 256, "end": 259, "text": ["have", "already", "been", "paid"], "event": "Ransom"}, {"start": 263, "end": 265, "text": ["the", "MongoDB", "attack"], "event": "Ransom"}, {"start": 268, "end": 270, "text": ["paying", "the", "ransom"], "event": "Ransom"}], "Entities": [[], [{"start": 216, "end": 217, "text": ["erasing", "data"], "type": "Capabilities"}, {"start": 212, "end": 212, "text": ["hackers"], "type": "Person"}, {"start": 220, "end": 220, "text": ["victims"], "type": "Person"}], [{"start": 5, "end": 6, "text": ["MongoDB", "databases"], "type": "System"}, {"start": 13, "end": 13, "text": ["cybercriminals"], "type": "Person"}, {"start": 19, "end": 20, "text": ["ElasticSearch", "servers"], "type": "System"}], [{"start": 29, "end": 31, "text": ["hijacked", "insecure", "servers"], "type": "Vulnerability"}, {"start": 26, "end": 26, "text": ["Hackers"], "type": "Person"}, {"start": 37, "end": 44, "text": ["weak", "and", "easy", "-", "to", "-", "guess", "passwords"], "type": "Capabilities"}], [{"start": 89, "end": 90, "text": ["ElasticSearch", "servers"], "type": "System"}, {"start": 80, "end": 81, "text": ["the", "cybercriminals"], "type": "Person"}], [], [{"start": 236, "end": 237, "text": ["0.2", "Bitcoins"], "type": "Money"}, {"start": 230, "end": 231, "text": ["the", "cybercriminals"], "type": "Person"}], [{"start": 261, "end": 261, "text": ["victims"], "type": "Person"}, {"start": 252, "end": 253, "text": ["$", "20,000"], "type": "Money"}, {"start": 254, "end": 255, "text": ["in", "Bitcoins"], "type": "PaymentMethod"}], [], [{"start": 272, "end": 273, "text": ["the", "victims"], "type": "Person"}]], "Causal": [[], [{"start": 212, "end": 212, "text": ["hackers"], "type": "Person"}], [{"start": 13, "end": 13, "text": ["cybercriminals"], "type": "Person"}], [{"start": 29, "end": 31, "text": ["hijacked", "insecure", "servers"], "type": "Vulnerability"}, {"start": 26, "end": 26, "text": ["Hackers"], "type": "Person"}, {"start": 37, "end": 44, "text": ["weak", "and", "easy", "-", "to", "-", "guess", "passwords"], "type": "Capabilities"}], [{"start": 80, "end": 81, "text": ["the", "cybercriminals"], "type": "Person"}], [], [{"start": 230, "end": 231, "text": ["the", "cybercriminals"], "type": "Person"}], [], [], []], "Effect": [[], [{"start": 216, "end": 217, "text": ["erasing", "data"], "type": "Capabilities"}, {"start": 220, "end": 220, "text": ["victims"], "type": "Person"}], [{"start": 5, "end": 6, "text": ["MongoDB", "databases"], "type": "System"}, {"start": 19, "end": 20, "text": ["ElasticSearch", "servers"], "type": "System"}], [], [{"start": 89, "end": 90, "text": ["ElasticSearch", "servers"], "type": "System"}], [], [{"start": 236, "end": 237, "text": ["0.2", "Bitcoins"], "type": "Money"}], [{"start": 261, "end": 261, "text": ["victims"], "type": "Person"}, {"start": 252, "end": 253, "text": ["$", "20,000"], "type": "Money"}, {"start": 254, "end": 255, "text": ["in", "Bitcoins"], "type": "PaymentMethod"}], [], [{"start": 272, "end": 273, "text": ["the", "victims"], "type": "Person"}]]}