{"tokens": ["The", "largest", "NHS", "trust", "in", "England", "has", "been", "hit", "by", "a", "cyber-attack", "that", "could", "affect", "thousands", "of", "files", "across", "at", "least", "four", "London", "hospitals", ".", "Barts", "health", "trust", ",", "which", "runs", "five", "hospitals", "in", "east", "London", "\u2013", "the", "Royal", "London", ",", "St", "Bartholomew", "\u2019s", ",", "Whipps", "Cross", ",", "Mile", "End", "and", "Newham", "\u2013", "has", "sent", "a", "message", "to", "staff", "urging", "them", "not", "to", "open", "email", "attachments", "from", "unknown", "senders", ".", "\u201c", "We", "are", "urgently", "investigating", "this", "matter", "and", "have", "taken", "a", "number", "of", "drives", "offline", "as", "a", "precautionary", "measure", ",", "a", "Barts", "spokeswoman", "said", ".", "\u201c", "We", "have", "tried", "and", "tested", "contingency", "plans", "in", "place", "and", "are", "making", "every", "effort", "to", "ensure", "that", "patient", "care", "will", "not", "be", "affected", "\u201d", ".", "It", "was", "reported", "earlier", "on", "Friday", "that", "the", "trust", "had", "been", "targeted", "with", "ransomware", ",", "which", "is", "normally", "delivered", "via", "emails", "that", "trick", "the", "recipient", "into", "opening", "attachments", "and", "releasing", "malware", "on", "to", "their", "system", ".", "But", "the", "spokeswoman", "ruled", "out", "such", "an", "attack", "on", "Friday", "night", ".", "The", "trust", "has", "not", "said", "how", "much", "of", "its", "system", "has", "been", "affected", "by", "the", "attack", "or", "whether", "patient", "data", "has", "been", "compromised", "but", "it", "said", "it", "believed", "that", "most", "of", "the", "affected", "system", "was", "housing", "corporate", "data", ".", "The", "trust", "\u2019s", "filing", "system", "between", "departments", "has", "been", "turned", "off", "while", "the", "investigation", "takes", "place", ".", "Staff", "at", "the", "Royal", "Free", "London", "foundation", "trust", "were", "also", "warned", "to", "beware", "of", "attacks", "on", "Friday", ",", "the", "Guardian", "has", "learned", ".", "\u201c", "We", "have", "been", "informed", "of", "a", "major", "cyber-attack", "on", "NHS", "organisations", ".", "Please", "exercise", "extreme", "caution", "when", "opening", "any", "email", "attachments", "from", "unknown", "source", "or", "that", "do", "n\u2019t", "seem", "relevant", "to", "you", ".", "We", "will", "be", "carrying", "out", "security", "scans", "on", "all", "computers", "within", "the", "trust", "so", "please", "leave", "them", "switched", "on", "until", "further", "notice", ",", "\u201d", "wrote", "the", "trust", "\u2019s", "IT", "director", ",", "Tosh", "Mondal", ".", "A", "spokesman", "said", "the", "email", "was", "in", "reaction", "to", "the", "Barts", "attack", "and", "that", "the", "Royal", "Free", "London", ",", "as", "well", "as", "Barnet", "and", "Chase", "Farm", "hospitals", ",", "had", "not", "been", "affected", ".", "NHS", "Digital", "said", "it", "was", "aware", "that", "Barts", "had", "been", "infected", "by", "a", "\u201c", "virus", "which", "has", "affected", "their", "IT", "systems", "\u201d", ".", "A", "spokesperson", "said", ":", "\u201c", "This", "issue", "highlights", "the", "fact", "that", "there", "are", "threats", "to", "data", "security", "within", "the", "health", "and", "care", "sector", ",", "as", "with", "any", "other", "sector", ".", "We", "remain", "committed", "to", "supporting", "the", "protection", "of", "data", "with", "the", "highest", "possible", "security", "standards", ",", "high", "levels", "of", "security", "expertise", "from", "the", "centre", "and", "appropriate", "training", "and", "awareness", "of", "the", "risks", "for", "all", "staff", "\u201d", ".", "She", "declined", "to", "answer", "questions", "about", "whether", "other", "NHS", "trusts", "had", "been", "affected", ",", "how", "much", "data", "may", "have", "been", "affected", "and", "who", "may", "be", "behind", "the", "attack", ".", "In", "October", ",", "the", "Northern", "Lincolnshire", "and", "Goole", "foundation", "trust", "was", "hit", "by", "an", "attack", "in", "which", "malware", "was", "used", "to", "encrypt", "files", "and", "demand", "a", "ransom", "in", "order", "to", "restore", "access", ".", "The", "trust", "did", "not", "pay", "the", "ransom", "but", "was", "forced", "to", "cancel", "patient", "appointments", "as", "its", "systems", "were", "shut", "down", "to", "remove", "the", "virus", ".", "John", "Bambenek", ",", "a", "threat", "intelligence", "manager", "at", "the", "firm", "Fidelis", "Cybersecurity", ",", "said", ":", "\u201c", "The", "trouble", "is", "that", "local", "authorities", "and", "governments", "are", "n\u2019t", "very", "prepared", "and", "they", "have", "extremely", "valuable", "information", "that", "simply", "ca", "n\u2019t", "be", "lost", ",", "so", "they", "\u2019re", "a", "tempting", "target", "for", "cybercriminals", ".", "\u201c", "Cyber", "defence", "is", "essential", ",", "but", "it", "\u2019s", "no", "longer", "enough", ";", "organisations", "of", "all", "sizes", "need", "to", "invest", "in", "detecting", "threats", "as", "well", ".", "Only", "then", "will", "cyber", "criminals", "be", "caught", "early", "enough", "to", "expel", "them", "from", "the", "network", "before", "serious", "damage", "is", "done", "\u201d"], "Event 1": {"trigger": {"start": 478, "end": 480, "text": ["was", "hit"]}, "event_type": "Ransom", "argument": [{"start": 475, "end": 478, "text": ["Goole", "foundation", "trust"]}, {"start": 471, "end": 474, "text": ["the", "Northern", "Lincolnshire"]}, {"start": 469, "end": 470, "text": ["October"]}], "Causal": [], "Effect": [{"start": 475, "end": 478, "text": ["Goole", "foundation", "trust"]}, {"start": 471, "end": 474, "text": ["the", "Northern", "Lincolnshire"]}]}, "Event 2": {"trigger": {"start": 492, "end": 495, "text": ["demand", "a", "ransom"]}, "event_type": "Ransom", "argument": [{"start": 489, "end": 491, "text": ["encrypt", "files"]}, {"start": 485, "end": 486, "text": ["malware"]}], "Causal": [{"start": 489, "end": 491, "text": ["encrypt", "files"]}], "Effect": []}, "Event 3": {"trigger": {"start": 503, "end": 508, "text": ["did", "not", "pay", "the", "ransom"]}, "event_type": "Ransom", "argument": [{"start": 501, "end": 503, "text": ["The", "trust"]}, {"start": 516, "end": 518, "text": ["its", "systems"]}], "Causal": [], "Effect": [{"start": 501, "end": 503, "text": ["The", "trust"]}, {"start": 516, "end": 518, "text": ["its", "systems"]}]}, "Event 4": {"trigger": {"start": 143, "end": 144, "text": ["trick"]}, "event_type": "Phishing", "argument": [{"start": 147, "end": 149, "text": ["opening", "attachments"]}, {"start": 150, "end": 152, "text": ["releasing", "malware"]}, {"start": 126, "end": 127, "text": ["Friday"]}, {"start": 139, "end": 142, "text": ["delivered", "via", "emails"]}, {"start": 144, "end": 146, "text": ["the", "recipient"]}, {"start": 128, "end": 130, "text": ["the", "trust"]}, {"start": 134, "end": 135, "text": ["ransomware"]}], "Causal": [{"start": 147, "end": 149, "text": ["opening", "attachments"]}, {"start": 150, "end": 152, "text": ["releasing", "malware"]}, {"start": 139, "end": 142, "text": ["delivered", "via", "emails"]}], "Effect": [{"start": 144, "end": 146, "text": ["the", "recipient"]}, {"start": 128, "end": 130, "text": ["the", "trust"]}]}}