{"tokens": ["For", "those", "unfamiliar", "with", "the", "tool", ",", "Rsync", "(", "remote", "sync", ")", "is", "commonly", "used", "by", "hosting", "providers", ",", "ISPs", ",", "and", "IT", "departments", "to", "backup", "data", "between", "servers", ".", "The", "ISP", "in", "question", ",", "KWIC", "Internet", "in", "Simcoe", ",", "Ontario", ",", "fixed", "the", "Rsync", "problems", "after", "being", "notified", "by", "Salted", "Hash", ",", "but", "it", "is", "n\u2019t", "clear", "how", "long", "the", "company", "\u2019s", "customers", "were", "exposed", ".", "Via", "email", ",", "Vickery", "shared", "his", "latest", "findings", "with", "Salted", "Hash", "last", "week", ".", "[", "Learn", "about", "top", "security", "certifications", ":", "Who", "they", "'re", "for", ",", "what", "they", "cost", ",", "and", "which", "you", "need", ".", "Initially", ",", "Vickery", "discovered", "databases", "belonging", "to", "Annex", "Business", "Media", ",", "a", "publishing", "firm", "with", "offices", "in", "Simcoe", "and", "Aurora", ",", "Ontario", ".", "One", "of", "the", "exposed", "Annex", "databases", "stood", "out", "to", "him", ",", "as", "it", "contained", "the", "data", "from", "the", "2015", "Ashley", "Madison", "data", "breach", ".", "The", "other", "databases", "contained", "customer", "information", "(", "names", ",", "email", "addresses", ",", "etc.", ")", "Salted", "Hash", "reached", "out", "to", "Annex", "Business", "Media", "and", "asked", "about", "the", "Ashley", "Madison", "records", ",", "as", "well", "as", "to", "inform", "them", "about", "the", "more", "recent", "security", "problems", ",", "but", "the", "company", "did", "n\u2019t", "respond", "to", "questions", ".", "Additional", "digging", "led", "Vickery", "to", "discover", "that", "Annex", "was", "just", "one", "part", "of", "a", "larger", "data", "breach", ",", "one", "that", "affected", "all", "of", "KWIC", "Internet", "'s", "customers", ".", "\u201c", "I", "quickly", "realized", "that", "this", "one", "is", "going", "to", "be", "a", "real", "mess", "for", "someone", "to", "clean", "up", "and", "quite", "a", "headache", "to", "determine", "all", "the", "affected", "parties", ",", "\u201d", "Vickery", "told", "Salted", "Hash", ".", "In", "all", ",", "there", "were", "terabytes", "of", "KWIC", "data", "exposed", "by", "the", "breach", ".", "The", "information", "inside", "the", "leaked", "databases", "included", "credit", "card", "details", ",", "email", "addresses", ",", "passwords", ",", "names", ",", "home", "and", "business", "addresses", ",", "phone", "numbers", ",", "email", "backups", ",", "VPN", "details", "and", "credentials", ",", "internal", "KWIC", "backups", ",", "and", "more", ".", "The", "KWIC", "archives", "also", "included", "a", "common", "PHP", "shell", "named", "r57", ",", "and", "a", "PHP", "-", "based", "DDoS", "tool", ",", "suggesting", "that", "the", "company", "had", "been", "hacked", "at", "some", "point", "prior", "to", "leaking", "their", "backups", "to", "the", "public", ".", "\u201c", "There", "are", "dozens", "of", "SQL", "database", "backup", "files", "and", "thousands", "of", "email", "backup", "directories", "containing", "everything", "from", "internal", "KWIC", "staff", "login", "credentials", "to", "police", "warrants", "for", "ISP", "subscriber", "information", ",", "\u201d", "Vickery", "said", ".", "Other", "customers", "exposed", "by", "the", "KWIC", "data", "breach", "include", "at", "least", "one", "law", "firm", ",", "Norfolk", "County", "(", "norfolkcounty.ca", ")", ",", "United", "Way", "(", "unitedwayhn.on.ca", ")", ",", "and", "Greenfield", "Dental", "Health", "Group", "(", "greenfielddentistry.ca", ")", ".", "In", "March", "of", "2016", ",", "Malwarebytes", "researcher", "J\u00e9r\u00f4me", "Segura", "discovered", "a", "KWIC", "customer", ",", "Norfolk", "General", "Hospital", ",", "had", "a", "compromised", "Joomla", "install", "that", "was", "being", "used", "to", "distribute", "Ransomware", ".", "When", "Segura", "reached", "out", "to", "contact", "the", "hospital", "about", "the", "incident", ",", "they", "did", "n\u2019t", "respond", "right", "away", "because", "the", "notification", "was", "viewed", "as", "a", "sales", "pitch", ".", "KWIC", "thought", "a", "second", "Malwarebytes", "notification", "was", "a", "Phishing", "attack", ".", "There", "are", "a", "number", "of", "unknowns", "connected", "to", "this", "incident", ",", "including", "the", "root", "cause", ",", "the", "number", "of", "people", "and", "businesses", "affected", ",", "and", "again", "-", "the", "length", "of", "time", "the", "data", "remained", "exposed", "to", "the", "public", ".", "Other", "questions", "focus", "on", "the", "PHP", "shell", "scripts", "and", "DDoS", "tools", ",", "why", "were", "they", "there", "?", "KWIC", "was", "contacted", "immediately", "after", "Salted", "Hash", "was", "informed", "about", "the", "data", "breach", ".", "It", "took", "multiple", "attempts", ",", "as", "the", "company", "does", "n't", "have", "phone", "support", "after", "8:00", "p.m.", "on", "weekdays", ",", "3:00", "p.m.", "on", "Saturdays", "(", "they", "'re", "closed", "Sunday", ")", ",", "but", "KWIC", "eventually", "responded", "via", "email", ".", "Twenty", "-", "four", "hours", "after", "being", "notified", ",", "the", "company", "stated", "the", "Rsync", "issues", "were", "fixed", ",", "However", ",", "they", "have", "n't", "answered", "any", "of", "the", "other", "follow", "-", "up", "questions", "asked", "by", "Salted", "Hash", ".", "On", "Tuesday", ",", "via", "email", ",", "the", "company", "said", "an", "audit", "was", "underway", "and", "affected", "customers", "would", "be", "notified", "once", "it", "is", "complete"], "Event 1": {"trigger": {"start": 47, "end": 49, "text": ["being", "notified"]}, "event_type": "DiscoverVulnerability", "argument": [{"start": 50, "end": 52, "text": ["Salted", "Hash"]}], "Causal": [{"start": 50, "end": 52, "text": ["Salted", "Hash"]}], "Effect": []}, "Event 2": {"trigger": {"start": 72, "end": 75, "text": ["his", "latest", "findings"]}, "event_type": "DiscoverVulnerability", "argument": [{"start": 70, "end": 71, "text": ["Vickery"]}, {"start": 78, "end": 80, "text": ["last", "week"]}, {"start": 76, "end": 78, "text": ["Salted", "Hash"]}], "Causal": [{"start": 70, "end": 71, "text": ["Vickery"]}, {"start": 76, "end": 78, "text": ["Salted", "Hash"]}], "Effect": []}, "Event 3": {"trigger": {"start": 146, "end": 148, "text": ["data", "breach"]}, "event_type": "Databreach", "argument": [{"start": 139, "end": 141, "text": ["the", "data"]}, {"start": 130, "end": 131, "text": ["databases"]}, {"start": 129, "end": 130, "text": ["Annex"]}, {"start": 144, "end": 146, "text": ["Ashley", "Madison"]}, {"start": 143, "end": 144, "text": ["2015"]}], "Causal": [], "Effect": [{"start": 139, "end": 141, "text": ["the", "data"]}, {"start": 130, "end": 131, "text": ["databases"]}, {"start": 129, "end": 130, "text": ["Annex"]}, {"start": 144, "end": 146, "text": ["Ashley", "Madison"]}]}, "Event 4": {"trigger": {"start": 214, "end": 218, "text": ["a", "larger", "data", "breach"]}, "event_type": "Databreach", "argument": [{"start": 227, "end": 228, "text": ["customers"]}, {"start": 208, "end": 209, "text": ["Annex"]}, {"start": 224, "end": 226, "text": ["KWIC", "Internet"]}], "Causal": [], "Effect": [{"start": 227, "end": 228, "text": ["customers"]}, {"start": 208, "end": 209, "text": ["Annex"]}, {"start": 224, "end": 226, "text": ["KWIC", "Internet"]}]}, "Event 5": {"trigger": {"start": 274, "end": 278, "text": ["exposed", "by", "the", "breach"]}, "event_type": "Databreach", "argument": [{"start": 305, "end": 307, "text": ["email", "backups"]}, {"start": 313, "end": 316, "text": ["internal", "KWIC", "backups"]}, {"start": 311, "end": 312, "text": ["credentials"]}, {"start": 308, "end": 310, "text": ["VPN", "details"]}, {"start": 286, "end": 289, "text": ["credit", "card", "details"]}, {"start": 290, "end": 292, "text": ["email", "addresses"]}, {"start": 293, "end": 294, "text": ["passwords"]}, {"start": 295, "end": 296, "text": ["names"]}, {"start": 297, "end": 301, "text": ["home", "and", "business", "addresses"]}, {"start": 302, "end": 304, "text": ["phone", "numbers"]}, {"start": 272, "end": 274, "text": ["KWIC", "data"]}, {"start": 279, "end": 281, "text": ["The", "information"]}, {"start": 282, "end": 285, "text": ["the", "leaked", "databases"]}], "Causal": [], "Effect": [{"start": 305, "end": 307, "text": ["email", "backups"]}, {"start": 313, "end": 316, "text": ["internal", "KWIC", "backups"]}, {"start": 311, "end": 312, "text": ["credentials"]}, {"start": 308, "end": 310, "text": ["VPN", "details"]}, {"start": 286, "end": 289, "text": ["credit", "card", "details"]}, {"start": 290, "end": 292, "text": ["email", "addresses"]}, {"start": 293, "end": 294, "text": ["passwords"]}, {"start": 295, "end": 296, "text": ["names"]}, {"start": 297, "end": 301, "text": ["home", "and", "business", "addresses"]}, {"start": 302, "end": 304, "text": ["phone", "numbers"]}, {"start": 272, "end": 274, "text": ["KWIC", "data"]}, {"start": 279, "end": 281, "text": ["The", "information"]}, {"start": 282, "end": 285, "text": ["the", "leaked", "databases"]}]}, "Event 6": {"trigger": {"start": 344, "end": 347, "text": ["had", "been", "hacked"]}, "event_type": "Databreach", "argument": [{"start": 352, "end": 358, "text": ["leaking", "their", "backups", "to", "the", "public"]}, {"start": 342, "end": 344, "text": ["the", "company"]}], "Causal": [{"start": 352, "end": 358, "text": ["leaking", "their", "backups", "to", "the", "public"]}], "Effect": [{"start": 342, "end": 344, "text": ["the", "company"]}]}, "Event 7": {"trigger": {"start": 400, "end": 402, "text": ["data", "breach"]}, "event_type": "Databreach", "argument": [{"start": 395, "end": 396, "text": ["customers"]}, {"start": 405, "end": 408, "text": ["one", "law", "firm"]}, {"start": 409, "end": 414, "text": ["Norfolk", "County", "(", "norfolkcounty.ca", ")"]}, {"start": 415, "end": 419, "text": ["United", "Way", "(", "unitedwayhn.on.ca"]}, {"start": 422, "end": 429, "text": ["Greenfield", "Dental", "Health", "Group", "(", "greenfielddentistry.ca", ")"]}], "Causal": [], "Effect": [{"start": 395, "end": 396, "text": ["customers"]}, {"start": 405, "end": 408, "text": ["one", "law", "firm"]}, {"start": 409, "end": 414, "text": ["Norfolk", "County", "(", "norfolkcounty.ca", ")"]}, {"start": 415, "end": 419, "text": ["United", "Way", "(", "unitedwayhn.on.ca"]}, {"start": 422, "end": 429, "text": ["Greenfield", "Dental", "Health", "Group", "(", "greenfielddentistry.ca", ")"]}]}, "Event 8": {"trigger": {"start": 566, "end": 569, "text": ["the", "data", "breach"]}, "event_type": "Databreach", "argument": [{"start": 556, "end": 557, "text": ["KWIC"]}], "Causal": [], "Effect": [{"start": 556, "end": 557, "text": ["KWIC"]}]}, "Event 9": {"trigger": {"start": 42, "end": 43, "text": ["fixed"]}, "event_type": "PatchVulnerability", "argument": [{"start": 35, "end": 37, "text": ["KWIC", "Internet"]}, {"start": 43, "end": 46, "text": ["the", "Rsync", "problems"]}], "Causal": [{"start": 35, "end": 37, "text": ["KWIC", "Internet"]}, {"start": 43, "end": 46, "text": ["the", "Rsync", "problems"]}], "Effect": []}, "Event 10": {"trigger": {"start": 496, "end": 499, "text": ["a", "Phishing", "attack"]}, "event_type": "Phishing", "argument": [{"start": 489, "end": 490, "text": ["KWIC"]}, {"start": 491, "end": 494, "text": ["a", "second", "Malwarebytes"]}], "Causal": [], "Effect": [{"start": 489, "end": 490, "text": ["KWIC"]}]}}